<?xml version="1.0"?>
<definitions>
	<definition>
		<key>text_product</key>
		<value><![CDATA[Товары]]></value>
	</definition>
	<definition>
		<key>text_error</key>
		<value><![CDATA[Бренд не найден!]]></value>
	</definition>
	<definition>
		<key>text_empty</key>
		<value><![CDATA[В этом списке нет товаров от этого бренда.]]></value>
	</definition>
	<definition>
		<key>text_stars</key>
		<value><![CDATA[%s из 5 звезд!]]></value>
	</definition>
	<definition>
		<key>text_sort</key>
		<value><![CDATA[Сортировать по:]]></value>
	</definition>
	<definition>
		<key>text_default</key>
		<value><![CDATA[По умолчанию]]></value>
	</definition>
	<definition>
		<key>text_name_asc</key>
		<value><![CDATA[Имя: A - Я]]></value>
	</definition>
	<definition>
		<key>text_name_desc</key>
		<value><![CDATA[Имя: Я - А]]></value>
	</definition>
	<definition>
		<key>text_price_asc</key>
		<value><![CDATA[Цена: Низкая &gt; Высокая]]></value>
	</definition>
	<definition>
		<key>text_price_desc</key>
		<value><![CDATA[Цена: Высокая &gt; Низкая]]></value>
	</definition>
	<definition>
		<key>text_rating_asc</key>
		<value><![CDATA[Рейтинг: Низкий]]></value>
	</definition>
	<definition>
		<key>text_rating_desc</key>
		<value><![CDATA[Рейтинг: Высокий]]></value>
	</definition>
</definitions>
